mesha/__init__.py
mesha/main.py
mesha-0.0.6.dist-info/licenses/LICENSE
mesha-0.0.6.dist-info/METADATA
mesha-0.0.6.dist-info/WHEEL
mesha-0.0.6.dist-info/top_level.txt
mesha-0.0.6.dist-info/RECORD
