Metadata-Version: 2.4
Name: mesha
Version: 0.0.6
Summary: A simple package for learning packaging our modules and make them available to be installed via pip.
Author-email: Hüseyin Özen Albayrak <210315026@ogr.cbu.edu.tr>, Mustafa Esen <210315060@ogr.cbu.edu.tr>, Egemen Saygın <210315063@ogr.cbu.edu.tr>, Seymen Kocatürk <220315088@ogr.cbu.edu.tr>, Arda Ömer <210315089@ogr.cbu.edu.tr>
License: MIT License
Project-URL: Homepage, https://github.com/huseyinozenalbayrak/python-mesha
Keywords: mustafa,egemen,seymen,hüseyin,arda,python
Classifier: Development Status :: 3 - Alpha
Classifier: Intended Audience :: Developers
Classifier: License :: OSI Approved :: MIT License
Classifier: Programming Language :: Python :: 3
Classifier: Operating System :: OS Independent
Requires-Python: >=3.6.0
License-File: LICENSE
Dynamic: license-file
